text_log_check/__init__.py
text_log_check/main.py
text_log_check/package.py
text_log_check-0.1.1.dist-info/LICENSE
text_log_check-0.1.1.dist-info/METADATA
text_log_check-0.1.1.dist-info/WHEEL
text_log_check-0.1.1.dist-info/top_level.txt
text_log_check-0.1.1.dist-info/RECORD
