Metadata-Version: 2.1
Name: text-log-check
Version: 0.1.1
Summary: A Python package for analyzing, verifying, and monitoring text-based log files. Includes tools for file existence checks, log tail analysis, text searches, and more.
Home-page: https://github.com/LibSecSource/text-log-check
Author: quillcraftsman
Author-email: quill@craftsman.lol
Project-URL: Documentation, https://libsecsource.github.io/text-log-check/
Project-URL: Source, https://github.com/LibSecSource/text-log-check
Project-URL: Tracker, https://github.com/LibSecSource/text-log-check/issues
Project-URL: Release notes, https://github.com/LibSecSource/text-log-check/releases
Project-URL: Changelog, https://github.com/LibSecSource/text-log-check/releases
Project-URL: Download, https://pypi.org/project/text-log-check/
Keywords: python,security,log-analysis
Classifier: Development Status :: 4 - Beta
Classifier: Intended Audience :: Developers
Classifier: Intended Audience :: System Administrators
Classifier: License :: OSI Approved
Classifier: License :: Public Domain
Classifier: License :: Other/Proprietary License
Classifier: Programming Language :: Python :: 3
Classifier: Operating System :: OS Independent
Classifier: Topic :: Security
Classifier: Topic :: System :: Monitoring
Classifier: Topic :: Utilities
Classifier: Topic :: Software Development :: Libraries :: Python Modules
Requires-Python: >=3
License-File: LICENSE
